intercoolerjs/__init__.py
intercoolerjs/models.py
intercoolerjs/static/intercoolerjs/js/intercooler.min.js
intercoolerjs/static/intercoolerjs/js/intercoolerjs.license
intercoolerjs/static/intercoolerjs/js/jquery.js
intercoolerjs/static/intercoolerjs/js/jquery.license
intercoolerjs/static/intercoolerjs/js/zepto.license
intercoolerjs/static/intercoolerjs/js/zepto.min.js
django_intercoolerjs-1.2.3.0.dist-info/LICENSE
django_intercoolerjs-1.2.3.0.dist-info/METADATA
django_intercoolerjs-1.2.3.0.dist-info/WHEEL
django_intercoolerjs-1.2.3.0.dist-info/top_level.txt
django_intercoolerjs-1.2.3.0.dist-info/RECORD
