Metadata-Version: 2.1
Name: django-intercoolerjs
Version: 1.2.3.0
Summary: Django wrapper for intercooler.js - AJAX With Attributes: There is no need to be complex.
Home-page: https://github.com/brejoc/django-intercoolerjs
Author: Jochen Breuer
Author-email: brejoc@gmail.com
License: MIT
Keywords: django,jquery,staticfiles,intercoolerjs
Platform: any
Classifier: Development Status :: 5 - Production/Stable
Classifier: Environment :: Web Environment
Classifier: Framework :: Django
Classifier: Intended Audience :: Developers
Classifier: Natural Language :: English
Classifier: License :: OSI Approved :: MIT License
Classifier: Operating System :: OS Independent
Classifier: Programming Language :: Python
Classifier: Topic :: Utilities
Requires-Dist: Django (>=1.3)
Requires-Dist: pypandoc
